dwd/__init__.py
dwd/cv.py
dwd/gen_dwd.py
dwd/gen_kern_dwd.py
dwd/kern_md.py
dwd/kernel_utils.py
dwd/linear_model.py
dwd/sim_fun.py
dwd/socp_dwd.py
dwd/svm.py
dwd/utils.py
dwd/viz.py
dwd-1.0.5.dist-info/LICENSE.txt
dwd-1.0.5.dist-info/WHEEL
dwd-1.0.5.dist-info/METADATA
dwd-1.0.5.dist-info/RECORD
