Metadata-Version: 2.1
Name: dwd
Version: 1.0.5
Summary: Distance Weighted Discrimination for Python
Author-email: Iain Carmichael <idc9@cornell.edu>, David Allemang <david.allemang@kitware.com>
Maintainer-email: Kitware Medical <david.allemang@kitware.com>
Requires-Python: >=3.6
Classifier: License :: OSI Approved :: MIT License
Classifier: Programming Language :: Python :: 3
Classifier: Programming Language :: Python :: 3.7
Classifier: Programming Language :: Python :: 3.7
Classifier: Programming Language :: Python :: 3 :: Only
Classifier: Development Status :: 4 - Beta
Classifier: Intended Audience :: Developers
Classifier: Intended Audience :: Science/Research
Classifier: Topic :: Scientific/Engineering
Classifier: Topic :: Scientific/Engineering :: Medical Science Apps.
Classifier: Topic :: Scientific/Engineering :: Information Analysis
Requires-Dist: numpy
Requires-Dist: scikit-learn
Requires-Dist: sphinx ; extra == "doc"
Requires-Dist: sphinx-rtd-theme ; extra == "doc"
Requires-Dist: cvxpy ; extra == "socp"
Project-URL: Source, https://github.com/slicersalt/dwd
Provides-Extra: doc
Provides-Extra: socp
Provides-Extra: test
